cactusgen/__init__.py
cactusgen/cactus.py
cactusgen/jrandom.py
cactusgen-1.0.1.dist-info/WHEEL
cactusgen-1.0.1.dist-info/METADATA
cactusgen-1.0.1.dist-info/RECORD
